hello.py
pyplines-0.0.0.dist-info/METADATA
pyplines-0.0.0.dist-info/WHEEL
pyplines-0.0.0.dist-info/top_level.txt
pyplines-0.0.0.dist-info/RECORD
