Metadata-Version: 2.4
Name: pyplines
Version: 0.0.0
Summary: Automation Pipelines in Python
Requires-Python: >=3.8
